Metadata-Version: 1.0
Name: decorrators
Version: 0.1.1.1b0
Summary: this is a python library with cool decorators
Home-page: UNKNOWN
Author: UNKNOWN
Author-email: vanshnir@gmail.com
License: UNKNOWN
Platform: UNKNOWN
